hex_gym/__init__.py
hex_gym/envs/__init__.py
hex_gym/envs/pod_env.py
hex_gym-1.0.0.dist-info/METADATA
hex_gym-1.0.0.dist-info/WHEEL
hex_gym-1.0.0.dist-info/top_level.txt
hex_gym-1.0.0.dist-info/RECORD
