Metadata-Version: 2.1
Name: hex-gym
Version: 1.0.0
Summary: A OpenAi Gym Environment for a hexapod
Home-page: UNKNOWN
License: UNKNOWN
Platform: UNKNOWN
Requires-Dist: gym
Requires-Dist: pybullet
Requires-Dist: numpy
